database_mcp/__init__.py
database_mcp/__main__.py
database_mcp/mcp_server.py
database_mcp_fastmcp-0.1.5.dist-info/licenses/LICENSE
database_mcp_fastmcp-0.1.5.dist-info/METADATA
database_mcp_fastmcp-0.1.5.dist-info/WHEEL
database_mcp_fastmcp-0.1.5.dist-info/entry_points.txt
database_mcp_fastmcp-0.1.5.dist-info/top_level.txt
database_mcp_fastmcp-0.1.5.dist-info/RECORD
