Metadata-Version: 2.4
Name: database-mcp-fastmcp
Version: 0.1.5
Summary: A MCP server that helps access and query data in various popular databases
Author-email: Legion AI <luke@thelegionai.com>
License-Expression: GPL-3.0-or-later
Project-URL: Homepage, https://github.com/fastmcp-me/legion-mcp#readme
Project-URL: Repository, https://github.com/fastmcp-me/legion-mcp.git
Project-URL: Issues, https://github.com/fastmcp-me/legion-mcp/issues
Requires-Python: >=3.10
License-File: LICENSE
Requires-Dist: legion-query-runner>=0.1.3
Requires-Dist: python-dotenv>=1.0.0
Requires-Dist: mcp>=1.0.0
Provides-Extra: dev
Requires-Dist: pytest>=7.4.2; extra == "dev"
Requires-Dist: mcp[cli]>=1.0.0; extra == "dev"
Dynamic: license-file
